safetext/__init__.py
safetext/utils.py
safetext/languages/ar/words.txt
safetext/languages/az/words.txt
safetext/languages/ch/words.txt
safetext/languages/de/words.txt
safetext/languages/en/words.txt
safetext/languages/es/words.txt
safetext/languages/fa/words.txt
safetext/languages/fr/words.txt
safetext/languages/hi/words.txt
safetext/languages/ja/words.txt
safetext/languages/ko/words.txt
safetext/languages/pt/words.txt
safetext/languages/ru/words.txt
safetext/languages/tr/words.txt
safetext/languages/zh/words.txt
safetext-0.3.2.dist-info/licenses/LICENSE
safetext-0.3.2.dist-info/METADATA
safetext-0.3.2.dist-info/WHEEL
safetext-0.3.2.dist-info/top_level.txt
safetext-0.3.2.dist-info/RECORD
