Metadata-Version: 2.4
Name: safetext
Version: 0.3.2
Summary: Fast profanity filtering tool for multiple languages
Author: Viddexa AI
License-Expression: MIT
Project-URL: Homepage, https://github.com/viddexa/safetext
Project-URL: Source, https://github.com/viddexa/safetext
Project-URL: Issues, https://github.com/viddexa/safetext/discussions/categories/q-a
Project-URL: Changelog, https://github.com/viddexa/safetext/releases
Keywords: text,profanity,filtering,moderation,turkish,english,spanish,arabic,hindi,chinese,portuguese,russian,french,german,japanese,persian,azerbaijani
Classifier: Development Status :: 5 - Production/Stable
Classifier: Operating System :: OS Independent
Classifier: Intended Audience :: Developers
Classifier: Intended Audience :: Science/Research
Classifier: Programming Language :: Python :: 3
Classifier: Programming Language :: Python :: 3.10
Classifier: Programming Language :: Python :: 3.11
Classifier: Programming Language :: Python :: 3.12
Classifier: Programming Language :: Python :: 3.13
Classifier: Topic :: Software Development :: Libraries
Classifier: Topic :: Software Development :: Libraries :: Python Modules
Classifier: Topic :: Education
Classifier: Topic :: Scientific/Engineering
Classifier: Topic :: Scientific/Engineering :: Artificial Intelligence
Requires-Python: >=3.10
License-File: LICENSE
Requires-Dist: lingua-language-detector==2.1.1
Requires-Dist: pysrt
Requires-Dist: requests
Requires-Dist: python-dotenv
Provides-Extra: dev
Requires-Dist: ruff>=0.1.0; extra == "dev"
Requires-Dist: pytest>=6.0; extra == "dev"
Requires-Dist: pytest-cov>=2.0; extra == "dev"
Requires-Dist: pytest-xdist>=3.0; extra == "dev"
Requires-Dist: twine>=4.0.0; extra == "dev"
Requires-Dist: build>=0.10.0; extra == "dev"
Provides-Extra: tests
Requires-Dist: pytest>=6.0; extra == "tests"
Requires-Dist: pytest-cov>=2.0; extra == "tests"
Dynamic: license-file
